prejudice-0.1.dist-info/METADATA
prejudice-0.1.dist-info/RECORD
prejudice-0.1.dist-info/top_level.txt
prejudice-0.1.dist-info/WHEEL
prejudice/errors.c
prejudice/types.py
prejudice/utils.c
prejudice/__init__.py
prejudice/errors.pyx
prejudice/utils.pyx
prejudice/utils.cpython-310-x86_64-linux-gnu.so
prejudice/decorator.py
prejudice/validators.py
prejudice/errors.cpython-310-x86_64-linux-gnu.so
