Metadata-Version: 2.1
Name: prejudice
Version: 0.1
Summary: Python/Cython predicate/guard/validation system.
Home-page: https://github.com/HorsemanWSGI/prejudice
Author: Souheil CHELFOUH
Author-email: trollfot@gmail.com
License: ZPL
Download-URL: http://pypi.python.org/pypi/prejudice
Platform: UNKNOWN
Classifier: Environment :: Web Environment
Classifier: Intended Audience :: Developers
Classifier: License :: OSI Approved :: Zope Public License
Classifier: Programming Language :: Python :: 3.8
Classifier: Programming Language :: Python :: 3.9
Classifier: Programming Language :: Python :: 3.10
Provides-Extra: test
Requires-Dist: pytest ; extra == 'test'
